[{"Id":1,"HallId":1,"RowNum":1,"SeatNum":1,"PriceCategoryId":1},{"Id":2,"HallId":1,"RowNum":1,"SeatNum":2,"PriceCategoryId":1},{"Id":3,"HallId":1,"RowNum":1,"SeatNum":3,"PriceCategoryId":1},{"Id":4,"HallId":1,"RowNum":1,"SeatNum":4,"PriceCategoryId":1},{"Id":5,"HallId":1,"RowNum":1,"SeatNum":5,"PriceCategoryId":1},{"Id":6,"HallId":1,"RowNum":2,"SeatNum":6,"PriceCategoryId":2},{"Id":7,"HallId":1,"RowNum":2,"SeatNum":7,"PriceCategoryId":2},{"Id":8,"HallId":1,"RowNum":2,"SeatNum":8,"PriceCategoryId":2},{"Id":9,"HallId":1,"RowNum":2,"SeatNum":9,"PriceCategoryId":2},{"Id":10,"HallId":1,"RowNum":2,"SeatNum":10,"PriceCategoryId":2},{"Id":11,"HallId":1,"RowNum":3,"SeatNum":11,"PriceCategoryId":3},{"Id":12,"HallId":1,"RowNum":3,"SeatNum":12,"PriceCategoryId":3},{"Id":13,"HallId":2,"RowNum":1,"SeatNum":1,"PriceCategoryId":1},{"Id":14,"HallId":2,"RowNum":1,"SeatNum":2,"PriceCategoryId":1},{"Id":15,"HallId":2,"RowNum":1,"SeatNum":3,"PriceCategoryId":1},{"Id":16,"HallId":2,"RowNum":1,"SeatNum":4,"PriceCategoryId":1},{"Id":17,"HallId":2,"RowNum":2,"SeatNum":5,"PriceCategoryId":2},{"Id":18,"HallId":2,"RowNum":2,"SeatNum":6,"PriceCategoryId":2},{"Id":19,"HallId":2,"RowNum":2,"SeatNum":7,"PriceCategoryId":2},{"Id":20,"HallId":2,"RowNum":2,"SeatNum":8,"PriceCategoryId":2},{"Id":21,"HallId":2,"RowNum":3,"SeatNum":9,"PriceCategoryId":3},{"Id":22,"HallId":2,"RowNum":3,"SeatNum":10,"PriceCategoryId":3},{"Id":23,"HallId":2,"RowNum":3,"SeatNum":11,"PriceCategoryId":3},{"Id":24,"HallId":2,"RowNum":3,"SeatNum":12,"PriceCategoryId":3},{"Id":25,"HallId":3,"RowNum":1,"SeatNum":1,"PriceCategoryId":1},{"Id":26,"HallId":3,"RowNum":1,"SeatNum":2,"PriceCategoryId":1},{"Id":27,"HallId":3,"RowNum":1,"SeatNum":3,"PriceCategoryId":1},{"Id":28,"HallId":3,"RowNum":1,"SeatNum":4,"PriceCategoryId":1},{"Id":29,"HallId":3,"RowNum":1,"SeatNum":5,"PriceCategoryId":1},{"Id":30,"HallId":3,"RowNum":1,"SeatNum":6,"PriceCategoryId":1},{"Id":31,"HallId":3,"RowNum":2,"SeatNum":7,"PriceCategoryId":2},{"Id":32,"HallId":3,"RowNum":2,"SeatNum":8,"PriceCategoryId":2},{"Id":33,"HallId":3,"RowNum":2,"SeatNum":9,"PriceCategoryId":2},{"Id":34,"HallId":3,"RowNum":2,"SeatNum":10,"PriceCategoryId":2},{"Id":35,"HallId":3,"RowNum":3,"SeatNum":11,"PriceCategoryId":3},{"Id":36,"HallId":3,"RowNum":3,"SeatNum":12,"PriceCategoryId":3}]